repository_management_api/__init__.py
repository_management_api/auth.py
repository_management_api/main.py
repository_management_api-0.0.1.dist-info/licenses/LICENSE
repository_management_api-0.0.1.dist-info/METADATA
repository_management_api-0.0.1.dist-info/WHEEL
repository_management_api-0.0.1.dist-info/top_level.txt
repository_management_api-0.0.1.dist-info/RECORD
