Metadata-Version: 2.4
Name: repository-management-api
Version: 0.0.1
Summary: A FastAPI service for creating and managing Git repositories.
Requires-Python: >=3.12
License-File: LICENSE
Requires-Dist: pytest==8.*
Requires-Dist: asgi-lifespan
Requires-Dist: fastapi[all]
Requires-Dist: cognito-jwt-verifier
Dynamic: license-file
